Metadata-Version: 2.1
Name: pyinspect
Version: 0.1.0
Summary: Find and inspect python functions
Home-page: https://github.com/FedeClaudi/pyinspect
Author: Federico Claudi
License: UNKNOWN
Platform: UNKNOWN
Requires-Python: >=3.6,
Requires-Dist: rich (>=9.2.0)
Requires-Dist: numpy
Requires-Dist: google
Requires-Dist: bs4
Requires-Dist: click
Requires-Dist: requests
Provides-Extra: dev
Requires-Dist: coverage-badge ; extra == 'dev'
Requires-Dist: click ; extra == 'dev'
